pygnuutils/__init__.py
pygnuutils/__main__.py
pygnuutils/basename.py
pygnuutils/basenc.py
pygnuutils/exceptions.py
pygnuutils/filevercmp.py
pygnuutils/human_readable.py
pygnuutils/ls.py
pygnuutils/yes.py
pygnuutils/cli/__init__.py
pygnuutils/cli/basename.py
pygnuutils/cli/basenc.py
pygnuutils/cli/ls.py
pygnuutils/cli/yes.py
pygnuutils-0.1.1.dist-info/LICENSE
pygnuutils-0.1.1.dist-info/METADATA
pygnuutils-0.1.1.dist-info/WHEEL
pygnuutils-0.1.1.dist-info/entry_points.txt
pygnuutils-0.1.1.dist-info/top_level.txt
pygnuutils-0.1.1.dist-info/RECORD
