Metadata-Version: 2.1
Name: pygnuutils
Version: 0.1.1
Summary: A python implementation for GNU utils
Author-email: Matan Perelman <matan1008@gmail.com>
Maintainer-email: Matan Perelman <matan1008@gmail.com>
License:                     GNU GENERAL PUBLIC LICENSE
Project-URL: Homepage, https://github.com/matan1008/pygnuutils
Project-URL: Bug Reports, https://github.com/matan1008/pygnuutils/issues
Keywords: gnu,cli,coreutils
Classifier: Development Status :: 5 - Production/Stable
Classifier: License :: OSI Approved :: GNU General Public License v3 or later (GPLv3+)
Classifier: Programming Language :: Python :: 3
Classifier: Programming Language :: Python :: 3.7
Classifier: Programming Language :: Python :: 3.8
Classifier: Programming Language :: Python :: 3.9
Classifier: Programming Language :: Python :: 3.10
Classifier: Programming Language :: Python :: 3.11
Classifier: Programming Language :: Python :: 3 :: Only
Requires-Python: >=3.7
Provides-Extra: test
License-File: LICENSE
